news_summizr/__init__.py
news_summizr/main.py
news_summizr/prompts.py
news_summizr-2025.12.21232733.dist-info/METADATA
news_summizr-2025.12.21232733.dist-info/WHEEL
news_summizr-2025.12.21232733.dist-info/top_level.txt
news_summizr-2025.12.21232733.dist-info/RECORD
