Metadata-Version: 2.4
Name: news-summizr
Version: 2025.12.21232733
Summary: news-summizr extracts structured summaries from headlines, labeling key points like announcement, products, region for quick insight.
Author-email: news-summizr <hi@eugene.plus>
License: MIT
Project-URL: Homepage, https://github.com/chigwell/news-summizr
Requires-Python: >=3.9
Requires-Dist: langchain-llm7>=0.0.0
Requires-Dist: llmatch-messages>=0.0.0
Requires-Dist: langchain-core>=0.3.0
